ecodev_sankey/__init__.py
ecodev_sankey/constants.py
ecodev_sankey/db_model/__init__.py
ecodev_sankey/db_model/datapoint_base.py
ecodev_sankey/db_model/empty_datapoint_list_error.py
ecodev_sankey/db_model/node_datapoint_link.py
ecodev_sankey/db_model/retrievers/__init__.py
ecodev_sankey/db_model/retrievers/datapoint_retrievers.py
ecodev_sankey/db_model/retrievers/tree_node_retrievers.py
ecodev_sankey/db_model/tree_node.py
ecodev_sankey/methodo/__init__.py
ecodev_sankey/methodo/compute_sankey_data.py
ecodev_sankey/methodo/datapoint_processing.py
ecodev_sankey/methodo/filter_helpers.py
ecodev_sankey/methodo/hierarchy_processing.py
ecodev_sankey/methodo/process_input_file.py
ecodev_sankey-0.0.6.dist-info/LICENSE.md
ecodev_sankey-0.0.6.dist-info/METADATA
ecodev_sankey-0.0.6.dist-info/WHEEL
ecodev_sankey-0.0.6.dist-info/RECORD
